MANIFEST.in
README.md
conf.py
setup.py
version.py
exceldriver/__init__.py
exceldriver/addin.py
exceldriver/columns.py
exceldriver/excel.py
exceldriver/exceptions.py
exceldriver/path.py
exceldriver/tools.py
exceldriver/wb_template.py
exceldriver.egg-info/PKG-INFO
exceldriver.egg-info/SOURCES.txt
exceldriver.egg-info/dependency_links.txt
exceldriver.egg-info/requires.txt
exceldriver.egg-info/top_level.txt
exceldriver/workbook/__init__.py
exceldriver/workbook/create.py
exceldriver/workbook/exceptions.py
exceldriver/workbook/read.py